{
  "status": "OK",
  "copyright": "Copyright (c) 2026 The New York Times Company. All Rights Reserved.",
  "num_results": 15,
  "last_modified": "2025-10-11T08:14:06Z",
  "results": {
    "display_name": "Hardcover Fiction",
    "list_name": "Hardcover Fiction",
    "list_name_encoded": "hardcover-fiction",
    "previous_published_date": "2024-08-25",
    "published_date": "2024-09-01",
    "next_published_date": "2024-09-08",
    "bestsellers_date": "2024-08-17",
    "normal_list_ends_at": 15,
    "updated": "WEEKLY",
    "list_id": 1,
    "uri": "nyt://bestsellerslist/8d99f5c5-65b3-5c24-97af-5b8c55e9e705",
    "books": [
      {
        "age_group": "",
        "amazon_product_url": "https://www.amazon.com/dp/1250178630?tag=thenewyorktim-20",
        "article_chapter_link": "",
        "asterisk": 0,
        "author": "Kristin Hannah",
        "book_image": "https://static01.nyt.com/bestsellers/images/9781250178633.jpg",
        "book_image_height": 500,
        "book_image_width": 333,
        "book_review_link": "",
        "book_uri": "nyt://book/9ce735af-71cf-5ff3-a367-43ee07e3fdd7",
        "contributor": "by Kristin Hannah",
        "contributor_note": "",
        "created_date": "2025-10-11T08:22:18.311Z",
        "dagger": 0,
        "description": "A nurse follows her brother to serve during the Vietnam War and returns to a divided America.",
        "first_chapter_link": "",
        "price": "0.00",
        "primary_isbn10": "",
        "primary_isbn13": "9781250178633",
        "publisher": "St. Martin's",
        "rank": 1,
        "rank_last_week": 1,
        "sunday_review_link": "",
        "title": "THE WOMEN",
        "updated_date": "2025-10-11T08:22:18.311Z",
        "weeks_on_list": 28,
        "isbns": [
          {
            "isbn10": "",
            "isbn13": "9781250178633"
          }
        ],
        "buy_links": [
          {
            "name": "Amazon",
            "url": "https://www.amazon.com/dp/1250178630?tag=thenewyorktim-20"
          },
          {
            "name": "Apple Books",
            "url": "https://goto.applebooks.apple/9781250178633?at=10lIEQ"
          },
          {
            "name": "Barnes and Noble",
            "url": "https://www.anrdoezrs.net/click-7990613-11819508?url=https%3A%2F%2Fwww.barnesandnoble.com%2Fw%2F%3Fean%3D9781250178633"
          },
          {
            "name": "Books-A-Million",
            "url": "https://www.anrdoezrs.net/click-7990613-35140?url=https%3A%2F%2Fwww.booksamillion.com%2Fp%2FTHE%2BWOMEN%2FKristin%2BHannah%2F9781250178633"
          },
          {
            "name": "Bookshop.org",
            "url": "https://bookshop.org/a/3546/9781250178633"
          }
        ]
      },
      {
        "age_group": "",
        "amazon_product_url": "https://www.amazon.com/dp/195756878X?tag=thenewyorktim-20",
        "article_chapter_link": "",
        "asterisk": 0,
        "author": "Jennifer L. Armentrout",
        "book_image": "https://static01.nyt.com/bestsellers/images/9781957568782.jpg",
        "book_image_height": 500,
        "book_image_width": 333,
        "book_review_link": "",
        "book_uri": "nyt://book/c30bdb32-88d8-5412-a755-9b38e9a80f43",
        "contributor": "by Jennifer L. Armentrout",
        "contributor_note": "",
        "created_date": "2025-10-11T08:13:47.574Z",
        "dagger": 0,
        "description": "The fourth book in the Flesh and Fire series. Sera and Nyktos must prevent Kolis from destroying the realms.",
        "first_chapter_link": "",
        "price": "0.00",
        "primary_isbn10": "",
        "primary_isbn13": "9781957568782",
        "publisher": "Blue Box",
        "rank": 2,
        "rank_last_week": 0,
        "sunday_review_link": "",
        "title": "BORN OF BLOOD AND ASH",
        "updated_date": "2025-10-11T08:13:47.574Z",
        "weeks_on_list": 1,
        "isbns": [
          {
            "isbn10": "",
            "isbn13": "9781957568782"
          }
        ],
        "buy_links": [
          {
            "name": "Amazon",
            "url": "https://www.amazon.com/dp/195756878X?tag=thenewyorktim-20"
          },
          {
            "name": "Apple Books",
            "url": "https://goto.applebooks.apple/9781957568782?at=10lIEQ"
          },
          {
            "name": "Barnes and Noble",
            "url": "https://www.anrdoezrs.net/click-7990613-11819508?url=https%3A%2F%2Fwww.barnesandnoble.com%2Fw%2F%3Fean%3D9781957568782"
          },
          {
            "name": "Books-A-Million",
            "url": "https://www.anrdoezrs.net/click-7990613-35140?url=https%3A%2F%2Fwww.booksamillion.com%2Fp%2FBORN%2BOF%2BBLOOD%2BAND%2BASH%2FJennifer%2BL.%2BArmentrout%2F9781957568782"
          },
          {
            "name": "Bookshop.org",
            "url": "https://bookshop.org/a/3546/9781957568782"
          }
        ]
      },
      {
        "age_group": "",
        "amazon_product_url": "https://www.amazon.com/dp/1538765705?tag=thenewyorktim-20",
        "article_chapter_link": "",
        "asterisk": 0,
        "author": "Douglas Preston and Lincoln Child",
        "book_image": "https://static01.nyt.com/bestsellers/images/9781538765708.jpg",
        "book_image_height": 500,
        "book_image_width": 330,
        "book_review_link": "",
        "book_uri": "nyt://book/0839f7da-b098-5398-8015-1fe41cc5cba3",
        "contributor": "by Douglas Preston and Lincoln Child",
        "contributor_note": "",
        "created_date": "2025-10-11T08:13:47.702Z",
        "dagger": 0,
        "description": "The 22nd book in the Agent Pendergast series. A serial killer in Manhattan seems poised to outmaneuver Pendergast and Greene.",
        "first_chapter_link": "",
        "price": "0.00",
        "primary_isbn10": "",
        "primary_isbn13": "9781538765708",
        "publisher": "Grand Central",
        "rank": 3,
        "rank_last_week": 0,
        "sunday_review_link": "",
        "title": "ANGEL OF VENGEANCE",
        "updated_date": "2025-10-11T08:13:47.702Z",
        "weeks_on_list": 1,
        "isbns": [
          {
            "isbn10": "",
            "isbn13": "9781538765708"
          }
        ],
        "buy_links": [
          {
            "name": "Amazon",
            "url": "https://www.amazon.com/dp/1538765705?tag=thenewyorktim-20"
          },
          {
            "name": "Apple Books",
            "url": "https://goto.applebooks.apple/9781538765708?at=10lIEQ"
          },
          {
            "name": "Barnes and Noble",
            "url": "https://www.anrdoezrs.net/click-7990613-11819508?url=https%3A%2F%2Fwww.barnesandnoble.com%2Fw%2F%3Fean%3D9781538765708"
          },
          {
            "name": "Books-A-Million",
            "url": "https://www.anrdoezrs.net/click-7990613-35140?url=https%3A%2F%2Fwww.booksamillion.com%2Fp%2FANGEL%2BOF%2BVENGEANCE%2FDouglas%2BPreston%2Band%2BLincoln%2BChild%2F9781538765708"
          },
          {
            "name": "Bookshop.org",
            "url": "https://bookshop.org/a/3546/9781538765708"
          }
        ]
      },
      {
        "age_group": "",
        "amazon_product_url": "https://www.amazon.com/dp/0593498615?tag=thenewyorktim-20",
        "article_chapter_link": "",
        "asterisk": 0,
        "author": "Danielle Steel",
        "book_image": "https://static01.nyt.com/bestsellers/images/9780593498613.jpg",
        "book_image_height": 500,
        "book_image_width": 327,
        "book_review_link": "",
        "book_uri": "nyt://book/994c5bdf-00f7-5ec8-a544-5d41a9136792",
        "contributor": "by Danielle Steel",
        "contributor_note": "",
        "created_date": "2025-10-11T08:14:37.89Z",
        "dagger": 0,
        "description": "A book editor recognizes the trauma incurred by her partner during his military deployments and seeks to restore her sense of self.",
        "first_chapter_link": "",
        "price": "0.00",
        "primary_isbn10": "",
        "primary_isbn13": "9780593498613",
        "publisher": "Delacorte",
        "rank": 4,
        "rank_last_week": 0,
        "sunday_review_link": "",
        "title": "JOY",
        "updated_date": "2025-10-11T08:14:37.89Z",
        "weeks_on_list": 1,
        "isbns": [
          {
            "isbn10": "",
            "isbn13": "9780593498613"
          }
        ],
        "buy_links": [
          {
            "name": "Amazon",
            "url": "https://www.amazon.com/dp/0593498615?tag=thenewyorktim-20"
          },
          {
            "name": "Apple Books",
            "url": "https://goto.applebooks.apple/9780593498613?at=10lIEQ"
          },
          {
            "name": "Barnes and Noble",
            "url": "https://www.anrdoezrs.net/click-7990613-11819508?url=https%3A%2F%2Fwww.barnesandnoble.com%2Fw%2F%3Fean%3D9780593498613"
          },
          {
            "name": "Books-A-Million",
            "url": "https://www.anrdoezrs.net/click-7990613-35140?url=https%3A%2F%2Fwww.booksamillion.com%2Fp%2FJOY%2FDanielle%2BSteel%2F9780593498613"
          },
          {
            "name": "Bookshop.org",
            "url": "https://bookshop.org/a/3546/9780593498613"
          }
        ]
      },
      {
        "age_group": "",
        "amazon_product_url": "https://www.amazon.com/dp/1250899575?tag=thenewyorktim-20",
        "article_chapter_link": "",
        "asterisk": 0,
        "author": "Alison Espach",
        "book_image": "https://static01.nyt.com/bestsellers/images/9781250899576.jpg",
        "book_image_height": 500,
        "book_image_width": 329,
        "book_review_link": "",
        "book_uri": "nyt://book/0935eb9b-9320-5ed9-93e8-32cef229779e",
        "contributor": "by Alison Espach",
        "contributor_note": "",
        "created_date": "2025-10-11T08:22:17.003Z",
        "dagger": 0,
        "description": "A woman who is down on her luck forms an unexpected bond with the bride at a wedding in Rhode Island.",
        "first_chapter_link": "",
        "price": "0.00",
        "primary_isbn10": "",
        "primary_isbn13": "9781250899576",
        "publisher": "Holt",
        "rank": 5,
        "rank_last_week": 6,
        "sunday_review_link": "",
        "title": "THE WEDDING PEOPLE",
        "updated_date": "2025-10-11T08:22:17.003Z",
        "weeks_on_list": 3,
        "isbns": [
          {
            "isbn10": "",
            "isbn13": "9781250899576"
          }
        ],
        "buy_links": [
          {
            "name": "Amazon",
            "url": "https://www.amazon.com/dp/1250899575?tag=thenewyorktim-20"
          },
          {
            "name": "Apple Books",
            "url": "https://goto.applebooks.apple/9781250899576?at=10lIEQ"
          },
          {
            "name": "Barnes and Noble",
            "url": "https://www.anrdoezrs.net/click-7990613-11819508?url=https%3A%2F%2Fwww.barnesandnoble.com%2Fw%2F%3Fean%3D9781250899576"
          },
          {
            "name": "Books-A-Million",
            "url": "https://www.anrdoezrs.net/click-7990613-35140?url=https%3A%2F%2Fwww.booksamillion.com%2Fp%2FTHE%2BWEDDING%2BPEOPLE%2FAlison%2BEspach%2F9781250899576"
          },
          {
            "name": "Bookshop.org",
            "url": "https://bookshop.org/a/3546/9781250899576"
          }
        ]
      },
      {
        "age_group": "",
        "amazon_product_url": "https://www.amazon.com/dp/1649374046?tag=thenewyorktim-20",
        "article_chapter_link": "",
        "asterisk": 0,
        "author": "Rebecca Yarros",
        "book_image": "https://static01.nyt.com/bestsellers/images/9781649374042.jpg",
        "book_image_height": 500,
        "book_image_width": 309,
        "book_review_link": "",
        "book_uri": "nyt://book/106c2cf0-7d20-51b1-bad4-91c3ebcd131a",
        "contributor": "by Rebecca Yarros",
        "contributor_note": "",
        "created_date": "2025-10-11T08:21:40.121Z",
        "dagger": 0,
        "description": "Violet Sorrengail is urged by the commanding general, who also is her mother, to become a candidate for the elite dragon riders.",
        "first_chapter_link": "",
        "price": "0.00",
        "primary_isbn10": "",
        "primary_isbn13": "9781649374042",
        "publisher": "Red Tower",
        "rank": 6,
        "rank_last_week": 4,
        "sunday_review_link": "",
        "title": "FOURTH WING",
        "updated_date": "2025-10-11T08:21:40.121Z",
        "weeks_on_list": 67,
        "isbns": [
          {
            "isbn10": "",
            "isbn13": "9781649374042"
          }
        ],
        "buy_links": [
          {
            "name": "Amazon",
            "url": "https://www.amazon.com/dp/1649374046?tag=thenewyorktim-20"
          },
          {
            "name": "Apple Books",
            "url": "https://goto.applebooks.apple/9781649374042?at=10lIEQ"
          },
          {
            "name": "Barnes and Noble",
            "url": "https://www.anrdoezrs.net/click-7990613-11819508?url=https%3A%2F%2Fwww.barnesandnoble.com%2Fw%2F%3Fean%3D9781649374042"
          },
          {
            "name": "Books-A-Million",
            "url": "https://www.anrdoezrs.net/click-7990613-35140?url=https%3A%2F%2Fwww.booksamillion.com%2Fp%2FFOURTH%2BWING%2FRebecca%2BYarros%2F9781649374042"
          },
          {
            "name": "Bookshop.org",
            "url": "https://bookshop.org/a/3546/9781649374042"
          }
        ]
      },
      {
        "age_group": "",
        "amazon_product_url": "https://www.amazon.com/dp/1649374178?tag=thenewyorktim-20",
        "article_chapter_link": "",
        "asterisk": 0,
        "author": "Rebecca Yarros",
        "book_image": "https://static01.nyt.com/bestsellers/images/9781649374172.jpg",
        "book_image_height": 500,
        "book_image_width": 309,
        "book_review_link": "",
        "book_uri": "nyt://book/d3c570c9-3c3a-5c8b-a740-85ea5e92bfc9",
        "contributor": "by Rebecca Yarros",
        "contributor_note": "",
        "created_date": "2025-10-11T08:22:17.941Z",
        "dagger": 0,
        "description": "The second book in the Empyrean series. Violet Sorrengail\u2019s next round of training under the new vice commandant might require her to betray the man she loves.",
        "first_chapter_link": "",
        "price": "0.00",
        "primary_isbn10": "",
        "primary_isbn13": "9781649374172",
        "publisher": "Red Tower",
        "rank": 7,
        "rank_last_week": 7,
        "sunday_review_link": "",
        "title": "IRON FLAME",
        "updated_date": "2025-10-11T08:22:17.941Z",
        "weeks_on_list": 41,
        "isbns": [
          {
            "isbn10": "",
            "isbn13": "9781649374172"
          }
        ],
        "buy_links": [
          {
            "name": "Amazon",
            "url": "https://www.amazon.com/dp/1649374178?tag=thenewyorktim-20"
          },
          {
            "name": "Apple Books",
            "url": "https://goto.applebooks.apple/9781649374172?at=10lIEQ"
          },
          {
            "name": "Barnes and Noble",
            "url": "https://www.anrdoezrs.net/click-7990613-11819508?url=https%3A%2F%2Fwww.barnesandnoble.com%2Fw%2F%3Fean%3D9781649374172"
          },
          {
            "name": "Books-A-Million",
            "url": "https://www.anrdoezrs.net/click-7990613-35140?url=https%3A%2F%2Fwww.booksamillion.com%2Fp%2FIRON%2BFLAME%2FRebecca%2BYarros%2F9781649374172"
          },
          {
            "name": "Bookshop.org",
            "url": "https://bookshop.org/a/3546/9781649374172"
          }
        ]
      },
      {
        "age_group": "",
        "amazon_product_url": "https://www.amazon.com/dp/0593418913?tag=thenewyorktim-20",
        "article_chapter_link": "",
        "asterisk": 0,
        "author": "Liz Moore",
        "book_image": "https://static01.nyt.com/bestsellers/images/9780593418918.jpg",
        "book_image_height": 500,
        "book_image_width": 331,
        "book_review_link": "",
        "book_uri": "nyt://book/76d129f6-ab9c-591c-b25e-9a2758250c07",
        "contributor": "by Liz Moore",
        "contributor_note": "",
        "created_date": "2025-10-11T08:22:17.384Z",
        "dagger": 0,
        "description": "When a 13-year-old girl disappears from an Adirondack summer camp in 1975, secrets kept by the Van Laar family emerge.",
        "first_chapter_link": "",
        "price": "0.00",
        "primary_isbn10": "",
        "primary_isbn13": "9780593418918",
        "publisher": "Riverhead",
        "rank": 8,
        "rank_last_week": 8,
        "sunday_review_link": "",
        "title": "THE GOD OF THE WOODS",
        "updated_date": "2025-10-11T08:22:17.384Z",
        "weeks_on_list": 7,
        "isbns": [
          {
            "isbn10": "",
            "isbn13": "9780593418918"
          }
        ],
        "buy_links": [
          {
            "name": "Amazon",
            "url": "https://www.amazon.com/dp/0593418913?tag=thenewyorktim-20"
          },
          {
            "name": "Apple Books",
            "url": "https://goto.applebooks.apple/9780593418918?at=10lIEQ"
          },
          {
            "name": "Barnes and Noble",
            "url": "https://www.anrdoezrs.net/click-7990613-11819508?url=https%3A%2F%2Fwww.barnesandnoble.com%2Fw%2F%3Fean%3D9780593418918"
          },
          {
            "name": "Books-A-Million",
            "url": "https://www.anrdoezrs.net/click-7990613-35140?url=https%3A%2F%2Fwww.booksamillion.com%2Fp%2FTHE%2BGOD%2BOF%2BTHE%2BWOODS%2FLiz%2BMoore%2F9780593418918"
          },
          {
            "name": "Bookshop.org",
            "url": "https://bookshop.org/a/3546/9780593418918"
          }
        ]
      },
      {
        "age_group": "",
        "amazon_product_url": "https://www.amazon.com/dp/0063383616?tag=thenewyorktim-20",
        "article_chapter_link": "",
        "asterisk": 0,
        "author": "Julia Quinn",
        "book_image": "https://static01.nyt.com/bestsellers/images/9780063383616.jpg",
        "book_image_height": 500,
        "book_image_width": 400,
        "book_review_link": "",
        "book_uri": "nyt://book/7e4c11c4-5c08-5348-87b7-8f67b4db4be9",
        "contributor": "by Julia Quinn",
        "contributor_note": "",
        "created_date": "2025-10-11T08:13:48.5Z",
        "dagger": 0,
        "description": "The second book in the Bridgerton Collector\u2019s Edition series.",
        "first_chapter_link": "",
        "price": "0.00",
        "primary_isbn10": "",
        "primary_isbn13": "9780063383616",
        "publisher": "Avon",
        "rank": 9,
        "rank_last_week": 0,
        "sunday_review_link": "",
        "title": "OFFER FROM A GENTLEMAN AND ROMANCING MR. BRIDGERTON",
        "updated_date": "2025-10-11T08:13:48.5Z",
        "weeks_on_list": 1,
        "isbns": [
          {
            "isbn10": "",
            "isbn13": "9780063383616"
          }
        ],
        "buy_links": [
          {
            "name": "Amazon",
            "url": "https://www.amazon.com/dp/0063383616?tag=thenewyorktim-20"
          },
          {
            "name": "Apple Books",
            "url": "https://goto.applebooks.apple/9780063383616?at=10lIEQ"
          },
          {
            "name": "Barnes and Noble",
            "url": "https://www.anrdoezrs.net/click-7990613-11819508?url=https%3A%2F%2Fwww.barnesandnoble.com%2Fw%2F%3Fean%3D9780063383616"
          },
          {
            "name": "Books-A-Million",
            "url": "https://www.anrdoezrs.net/click-7990613-35140?url=https%3A%2F%2Fwww.booksamillion.com%2Fp%2FOFFER%2BFROM%2BA%2BGENTLEMAN%2BAND%2BROMANCING%2BMR.%2BBRIDGERTON%2FJulia%2BQuinn%2F9780063383616"
          },
          {
            "name": "Bookshop.org",
            "url": "https://bookshop.org/a/3546/9780063383616"
          }
        ]
      },
      {
        "age_group": "",
        "amazon_product_url": "https://www.amazon.com/dp/1250346746?tag=thenewyorktim-20",
        "article_chapter_link": "",
        "asterisk": 0,
        "author": "Harper L. Woods",
        "book_image": "https://static01.nyt.com/bestsellers/images/9781250358936.jpg",
        "book_image_height": 500,
        "book_image_width": 335,
        "book_review_link": "",
        "book_uri": "nyt://book/5f16bbe5-8d3b-59d0-adea-9fd64e2f305d",
        "contributor": "by Harper L. Woods",
        "contributor_note": "",
        "created_date": "2025-10-11T08:14:37.277Z",
        "dagger": 0,
        "description": "At Hollow\u2019s Grove University, a school for magic that suffered a bloody massacre decades ago, 13 gifted students confront ghosts from the school\u2019s past.",
        "first_chapter_link": "",
        "price": "0.00",
        "primary_isbn10": "",
        "primary_isbn13": "9781250358936",
        "publisher": "Bramble",
        "rank": 10,
        "rank_last_week": 2,
        "sunday_review_link": "",
        "title": "THE COVEN",
        "updated_date": "2025-10-11T08:14:37.277Z",
        "weeks_on_list": 2,
        "isbns": [
          {
            "isbn10": "",
            "isbn13": "9781250358936"
          }
        ],
        "buy_links": [
          {
            "name": "Amazon",
            "url": "https://www.amazon.com/dp/1250346746?tag=thenewyorktim-20"
          },
          {
            "name": "Apple Books",
            "url": "https://goto.applebooks.apple/9781250358936?at=10lIEQ"
          },
          {
            "name": "Barnes and Noble",
            "url": "https://www.anrdoezrs.net/click-7990613-11819508?url=https%3A%2F%2Fwww.barnesandnoble.com%2Fw%2F%3Fean%3D9781250358936"
          },
          {
            "name": "Books-A-Million",
            "url": "https://www.anrdoezrs.net/click-7990613-35140?url=https%3A%2F%2Fwww.booksamillion.com%2Fp%2FTHE%2BCOVEN%2FHarper%2BL.%2BWoods%2F9781250358936"
          },
          {
            "name": "Bookshop.org",
            "url": "https://bookshop.org/a/3546/9781250358936"
          }
        ]
      },
      {
        "age_group": "",
        "amazon_product_url": "https://www.amazon.com/dp/0593798872?tag=thenewyorktim-20",
        "article_chapter_link": "",
        "asterisk": 0,
        "author": "Chris Whitaker",
        "book_image": "https://static01.nyt.com/bestsellers/images/9780593798874.jpg",
        "book_image_height": 500,
        "book_image_width": 328,
        "book_review_link": "",
        "book_uri": "nyt://book/4a3574a1-cb25-5910-a11e-f97ffb3508bd",
        "contributor": "by Chris Whitaker",
        "contributor_note": "",
        "created_date": "2025-10-11T08:18:55.972Z",
        "dagger": 0,
        "description": "Questions arise when a boy saves the daughter of a wealthy family amid a string of disappearances in a Missouri town in 1975.",
        "first_chapter_link": "",
        "price": "0.00",
        "primary_isbn10": "",
        "primary_isbn13": "9780593798874",
        "publisher": "Crown",
        "rank": 11,
        "rank_last_week": 10,
        "sunday_review_link": "",
        "title": "ALL THE COLORS OF THE DARK",
        "updated_date": "2025-10-11T08:18:55.972Z",
        "weeks_on_list": 8,
        "isbns": [
          {
            "isbn10": "",
            "isbn13": "9780593798874"
          }
        ],
        "buy_links": [
          {
            "name": "Amazon",
            "url": "https://www.amazon.com/dp/0593798872?tag=thenewyorktim-20"
          },
          {
            "name": "Apple Books",
            "url": "https://goto.applebooks.apple/9780593798874?at=10lIEQ"
          },
          {
            "name": "Barnes and Noble",
            "url": "https://www.anrdoezrs.net/click-7990613-11819508?url=https%3A%2F%2Fwww.barnesandnoble.com%2Fw%2F%3Fean%3D9780593798874"
          },
          {
            "name": "Books-A-Million",
            "url": "https://www.anrdoezrs.net/click-7990613-35140?url=https%3A%2F%2Fwww.booksamillion.com%2Fp%2FALL%2BTHE%2BCOLORS%2BOF%2BTHE%2BDARK%2FChris%2BWhitaker%2F9780593798874"
          },
          {
            "name": "Bookshop.org",
            "url": "https://bookshop.org/a/3546/9780593798874"
          }
        ]
      },
      {
        "age_group": "",
        "amazon_product_url": "https://www.amazon.com/dp/1982182237?tag=thenewyorktim-20",
        "article_chapter_link": "",
        "asterisk": 0,
        "author": "Brad Thor",
        "book_image": "https://static01.nyt.com/bestsellers/images/9781982182236.jpg",
        "book_image_height": 500,
        "book_image_width": 327,
        "book_review_link": "",
        "book_uri": "nyt://book/706b16ed-d169-5ab5-93cb-20b551a387f4",
        "contributor": "by Brad Thor",
        "contributor_note": "",
        "created_date": "2025-10-11T08:13:48.915Z",
        "dagger": 0,
        "description": "The 23rd book in the Scot Harvath series. A mess of trouble involving double agents, international intrigue and a potential global firestorm forces Harvath to choose between his country and his conscience.",
        "first_chapter_link": "",
        "price": "0.00",
        "primary_isbn10": "",
        "primary_isbn13": "9781982182236",
        "publisher": "Atria/Emily Bestler",
        "rank": 12,
        "rank_last_week": 3,
        "sunday_review_link": "",
        "title": "SHADOW OF DOUBT",
        "updated_date": "2025-10-11T08:13:48.915Z",
        "weeks_on_list": 2,
        "isbns": [
          {
            "isbn10": "",
            "isbn13": "9781982182236"
          }
        ],
        "buy_links": [
          {
            "name": "Amazon",
            "url": "https://www.amazon.com/dp/1982182237?tag=thenewyorktim-20"
          },
          {
            "name": "Apple Books",
            "url": "https://goto.applebooks.apple/9781982182236?at=10lIEQ"
          },
          {
            "name": "Barnes and Noble",
            "url": "https://www.anrdoezrs.net/click-7990613-11819508?url=https%3A%2F%2Fwww.barnesandnoble.com%2Fw%2F%3Fean%3D9781982182236"
          },
          {
            "name": "Books-A-Million",
            "url": "https://www.anrdoezrs.net/click-7990613-35140?url=https%3A%2F%2Fwww.booksamillion.com%2Fp%2FSHADOW%2BOF%2BDOUBT%2FBrad%2BThor%2F9781982182236"
          },
          {
            "name": "Bookshop.org",
            "url": "https://bookshop.org/a/3546/9781982182236"
          }
        ]
      },
      {
        "age_group": "",
        "amazon_product_url": "https://www.amazon.com/dp/0316576794?tag=thenewyorktim-20",
        "article_chapter_link": "",
        "asterisk": 0,
        "author": "T.J. Newman",
        "book_image": "https://static01.nyt.com/bestsellers/images/9780316576796.jpg",
        "book_image_height": 500,
        "book_image_width": 323,
        "book_review_link": "",
        "book_uri": "nyt://book/30b6b0f8-003d-5acd-81d2-4343f0588afd",
        "contributor": "by T.J. Newman",
        "contributor_note": "",
        "created_date": "2025-10-11T08:13:49.052Z",
        "dagger": 0,
        "description": "When a commercial airliner crashes into a nuclear power plant, firefighters, plant employees and nearby citizens go into action.",
        "first_chapter_link": "",
        "price": "0.00",
        "primary_isbn10": "",
        "primary_isbn13": "9780316576796",
        "publisher": "Little, Brown",
        "rank": 13,
        "rank_last_week": 0,
        "sunday_review_link": "",
        "title": "WORST CASE SCENARIO",
        "updated_date": "2025-10-11T08:13:49.052Z",
        "weeks_on_list": 1,
        "isbns": [
          {
            "isbn10": "",
            "isbn13": "9780316576796"
          }
        ],
        "buy_links": [
          {
            "name": "Amazon",
            "url": "https://www.amazon.com/dp/0316576794?tag=thenewyorktim-20"
          },
          {
            "name": "Apple Books",
            "url": "https://goto.applebooks.apple/9780316576796?at=10lIEQ"
          },
          {
            "name": "Barnes and Noble",
            "url": "https://www.anrdoezrs.net/click-7990613-11819508?url=https%3A%2F%2Fwww.barnesandnoble.com%2Fw%2F%3Fean%3D9780316576796"
          },
          {
            "name": "Books-A-Million",
            "url": "https://www.anrdoezrs.net/click-7990613-35140?url=https%3A%2F%2Fwww.booksamillion.com%2Fp%2FWORST%2BCASE%2BSCENARIO%2FT.J.%2BNewman%2F9780316576796"
          },
          {
            "name": "Bookshop.org",
            "url": "https://bookshop.org/a/3546/9780316576796"
          }
        ]
      },
      {
        "age_group": "",
        "amazon_product_url": "https://www.amazon.com/dp/0593722566?tag=thenewyorktim-20",
        "article_chapter_link": "",
        "asterisk": 0,
        "author": "Ava Reid",
        "book_image": "https://static01.nyt.com/bestsellers/images/9780593722565.jpg",
        "book_image_height": 500,
        "book_image_width": 331,
        "book_review_link": "",
        "book_uri": "nyt://book/da5c5a00-603b-5a71-b3a3-9b24a4211031",
        "contributor": "by Ava Reid",
        "contributor_note": "",
        "created_date": "2025-10-11T08:13:49.19Z",
        "dagger": 0,
        "description": "A reimagining of Shakespeare\u2019s \u201cMacbeth,\u201d which centers the story on Lady Macbeth.",
        "first_chapter_link": "",
        "price": "0.00",
        "primary_isbn10": "",
        "primary_isbn13": "9780593722565",
        "publisher": "Del Rey",
        "rank": 14,
        "rank_last_week": 0,
        "sunday_review_link": "",
        "title": "LADY MACBETH",
        "updated_date": "2025-10-11T08:13:49.19Z",
        "weeks_on_list": 1,
        "isbns": [
          {
            "isbn10": "",
            "isbn13": "9780593722565"
          }
        ],
        "buy_links": [
          {
            "name": "Amazon",
            "url": "https://www.amazon.com/dp/0593722566?tag=thenewyorktim-20"
          },
          {
            "name": "Apple Books",
            "url": "https://goto.applebooks.apple/9780593722565?at=10lIEQ"
          },
          {
            "name": "Barnes and Noble",
            "url": "https://www.anrdoezrs.net/click-7990613-11819508?url=https%3A%2F%2Fwww.barnesandnoble.com%2Fw%2F%3Fean%3D9780593722565"
          },
          {
            "name": "Books-A-Million",
            "url": "https://www.anrdoezrs.net/click-7990613-35140?url=https%3A%2F%2Fwww.booksamillion.com%2Fp%2FLADY%2BMACBETH%2FAva%2BReid%2F9780593722565"
          },
          {
            "name": "Bookshop.org",
            "url": "https://bookshop.org/a/3546/9780593722565"
          }
        ]
      },
      {
        "age_group": "",
        "amazon_product_url": "https://www.amazon.com/dp/0316569917?tag=thenewyorktim-20",
        "article_chapter_link": "",
        "asterisk": 0,
        "author": "James Patterson and Mike Lupica",
        "book_image": "https://static01.nyt.com/bestsellers/images/9780316569910.jpg",
        "book_image_height": 500,
        "book_image_width": 323,
        "book_review_link": "",
        "book_uri": "nyt://book/8f477d34-b35b-5cc1-b330-d84dfe67c1d5",
        "contributor": "by James Patterson and Mike Lupica",
        "contributor_note": "",
        "created_date": "2025-10-11T08:13:49.308Z",
        "dagger": 0,
        "description": "The second book in the Jane Smith series. A double triple homicide complicates matters for Smith.",
        "first_chapter_link": "",
        "price": "0.00",
        "primary_isbn10": "",
        "primary_isbn13": "9780316569910",
        "publisher": "Little, Brown",
        "rank": 15,
        "rank_last_week": 5,
        "sunday_review_link": "",
        "title": "HARD TO KILL",
        "updated_date": "2025-10-11T08:13:49.308Z",
        "weeks_on_list": 3,
        "isbns": [
          {
            "isbn10": "",
            "isbn13": "9780316569910"
          }
        ],
        "buy_links": [
          {
            "name": "Amazon",
            "url": "https://www.amazon.com/dp/0316569917?tag=thenewyorktim-20"
          },
          {
            "name": "Apple Books",
            "url": "https://goto.applebooks.apple/9780316569910?at=10lIEQ"
          },
          {
            "name": "Barnes and Noble",
            "url": "https://www.anrdoezrs.net/click-7990613-11819508?url=https%3A%2F%2Fwww.barnesandnoble.com%2Fw%2F%3Fean%3D9780316569910"
          },
          {
            "name": "Books-A-Million",
            "url": "https://www.anrdoezrs.net/click-7990613-35140?url=https%3A%2F%2Fwww.booksamillion.com%2Fp%2FHARD%2BTO%2BKILL%2FJames%2BPatterson%2Band%2BMike%2BLupica%2F9780316569910"
          },
          {
            "name": "Bookshop.org",
            "url": "https://bookshop.org/a/3546/9780316569910"
          }
        ]
      }
    ],
    "corrections": []
  }
}